__init__.py
file_loader/__init__.py
file_loader/file_loader.py
fileLoader-0.0.0.dist-info/LICENSE
fileLoader-0.0.0.dist-info/METADATA
fileLoader-0.0.0.dist-info/WHEEL
fileLoader-0.0.0.dist-info/top_level.txt
fileLoader-0.0.0.dist-info/RECORD
