Metadata-Version: 2.1
Name: fileLoader
Version: 0.0.0
Summary: Read files of any format into pandas with just read_file(**kwargs) method
Author-email: Bhanu Suraj Malla <bsmalla@asu.edu>
Project-URL: Homepage, https://github.com/mbsuraj/structuredDataLoader
Project-URL: Bug Tracker, https://github.com/mbsuraj/structuredDataLoader/issues
Classifier: Programming Language :: Python :: 3
Classifier: License :: OSI Approved :: MIT License
Classifier: Operating System :: OS Independent
Requires-Python: >=3.7
License-File: LICENSE
